windnd/__init__.py
windnd/windnd.py
pywindnd-1.0.9.dist-info/WHEEL
pywindnd-1.0.9.dist-info/METADATA
pywindnd-1.0.9.dist-info/license_files/LICENSE
pywindnd-1.0.9.dist-info/RECORD
