Metadata-Version: 2.1
Name: pywindnd
Version: 1.0.9
Summary: windows drag icon & drop to load absolute file path
License: MIT
Author-email: Ayden <2361018131@qq.com>
Requires-Python: >=3.8
Classifier: Programming Language :: Python
Project-URL: Homepage, https://pypi.org/project/pywindnd
Project-URL: Source Code, https://github.com/D-Ayden/pywindnd
